test_uni.py
uni.py
uc/__init__.py
uc/block.py
uc/format.py
uc/html.py
uc/search.py
uc/test_block.py
uc/test_format.py
uc/test_html.py
uc/test_search.py
uc/test_uni.py
uc/uni.py
uc/data/__init__.py
uc/data/block.py
uc/data/ccc.py
uc/data/html_entities.py
uc/data/make_html_entities.py
unicode_name_inquiry-1.9.3.dist-info/LICENSE
unicode_name_inquiry-1.9.3.dist-info/METADATA
unicode_name_inquiry-1.9.3.dist-info/WHEEL
unicode_name_inquiry-1.9.3.dist-info/entry_points.txt
unicode_name_inquiry-1.9.3.dist-info/top_level.txt
unicode_name_inquiry-1.9.3.dist-info/RECORD
